jupyter_remote_spawn
