Metadata-Version: 2.1
Name: rwth-jupyter
Version: 0.0.5
Summary: Start a RWTHjupyter instance on your machine
Home-page: https://git.rwth-aachen.de/jupyter/remote-spawn
Author: Steffen Vogel
Author-email: post@steffenvogel.de
License: UNKNOWN
Project-URL: Bug Tracker, https://git.rwth-aachen.de/jupyter/remote-spawn/-/issues
Platform: UNKNOWN
Classifier: Programming Language :: Python :: 3
Classifier: License :: OSI Approved :: MIT License
Classifier: Operating System :: OS Independent
Requires-Python: >=3.6
